[{"name":"sql.active_record","payload":{"sql":"SELECT  \"authors\".* FROM \"authors\"  WHERE \"authors\".\"id\" = $1 LIMIT 1","name":"Author Load","connection_id":70194975079220,"binds":[[{"name":"id","sql_type":"integer","null":false,"limit":null,"precision":null,"scale":null,"type":"integer","default":null,"primary":true,"coder":null},"13"]]},"time":"2013-07-04T10:37:29+10:00","transaction_id":"220d4036e2448bf236ad","end":"2013-07-04T10:37:29+10:00","duration":0.45},{"name":"render_template.action_view","payload":{"identifier":"/Users/willybuttvangelderen/Projects/portfolio/wdi/rails/books/app/views/authors/show.html.erb","layout":"layouts/application","exception":["ActionView::Template::Error","undefined method `each' for #<Author:0x007faf11310408>"]},"time":"2013-07-04T10:37:29+10:00","transaction_id":"9b50e7c8e6bfbdd7bc48","end":"2013-07-04T10:37:29+10:00","duration":55.857},{"name":"process_action.action_controller","payload":{"controller":"AuthorsController","action":"show","params":{"action":"show","controller":"authors","id":"13"},"format":"html","method":"GET","path":"/authors/13","exception":["ActionView::Template::Error","undefined method `each' for #<Author:0x007faf11310408>"],"status":"500"},"time":"2013-07-04T10:37:29+10:00","transaction_id":"9b50e7c8e6bfbdd7bc48","end":"2013-07-04T10:37:29+10:00","duration":60.835},{"name":"process_action.action_controller.exception","payload":{"call":"ActionView::Template::Error (undefined method `each' for #<Author:0x007faf11310408>)"},"time":0,"transaction_id":null,"end":0,"duration":0.0},{"name":"process_action.action_controller.exception","payload":{"call":"app/views/authors/show.html.erb:1:in `_app_views_authors_show_html_erb___648220696559830840_70194942210000'"},"time":0,"transaction_id":null,"end":0,"duration":0.0}]