[{"name":"sql.active_record","payload":{"sql":"SELECT  \"authors\".* FROM \"authors\"  WHERE \"authors\".\"id\" = $1 LIMIT 1","name":"Author Load","connection_id":70194975079220,"binds":[[{"name":"id","sql_type":"integer","null":false,"limit":null,"precision":null,"scale":null,"type":"integer","default":null,"primary":true,"coder":null},"13"]]},"time":"2013-07-04T10:35:14+10:00","transaction_id":"220d4036e2448bf236ad","end":"2013-07-04T10:35:14+10:00","duration":2.6470000000000002},{"name":"render_template.action_view","payload":{"identifier":"/Users/willybuttvangelderen/Projects/portfolio/wdi/rails/books/app/views/authors/show.html.erb","layout":"layouts/application","exception":["ActionView::Template::Error","undefined method `each' for #<Author:0x007faf141a03e0>"]},"time":"2013-07-04T10:35:14+10:00","transaction_id":"2928dc0c423585b9b461","end":"2013-07-04T10:35:14+10:00","duration":1.824},{"name":"process_action.action_controller","payload":{"controller":"AuthorsController","action":"show","params":{"action":"show","controller":"authors","id":"13"},"format":"html","method":"GET","path":"/authors/13","exception":["ActionView::Template::Error","undefined method `each' for #<Author:0x007faf141a03e0>"],"status":"500"},"time":"2013-07-04T10:35:14+10:00","transaction_id":"2928dc0c423585b9b461","end":"2013-07-04T10:35:14+10:00","duration":9.007},{"name":"process_action.action_controller.exception","payload":{"call":"ActionView::Template::Error (undefined method `each' for #<Author:0x007faf141a03e0>)"},"time":0,"transaction_id":null,"end":0,"duration":0.0},{"name":"process_action.action_controller.exception","payload":{"call":"app/views/authors/show.html.erb:1:in `_app_views_authors_show_html_erb___648220696559830840_70194967568760'"},"time":0,"transaction_id":null,"end":0,"duration":0.0}]